posthoganalytics/__init__.py
posthoganalytics/args.py
posthoganalytics/client.py
posthoganalytics/consumer.py
posthoganalytics/contexts.py
posthoganalytics/exception_capture.py
posthoganalytics/exception_utils.py
posthoganalytics/feature_flags.py
posthoganalytics/flag_definition_cache.py
posthoganalytics/poller.py
posthoganalytics/py.typed
posthoganalytics/request.py
posthoganalytics/types.py
posthoganalytics/utils.py
posthoganalytics/version.py
posthoganalytics/ai/__init__.py
posthoganalytics/ai/prompts.py
posthoganalytics/ai/sanitization.py
posthoganalytics/ai/types.py
posthoganalytics/ai/utils.py
posthoganalytics/ai/anthropic/__init__.py
posthoganalytics/ai/anthropic/anthropic.py
posthoganalytics/ai/anthropic/anthropic_async.py
posthoganalytics/ai/anthropic/anthropic_converter.py
posthoganalytics/ai/anthropic/anthropic_providers.py
posthoganalytics/ai/gemini/__init__.py
posthoganalytics/ai/gemini/gemini.py
posthoganalytics/ai/gemini/gemini_async.py
posthoganalytics/ai/gemini/gemini_converter.py
posthoganalytics/ai/langchain/__init__.py
posthoganalytics/ai/langchain/callbacks.py
posthoganalytics/ai/openai/__init__.py
posthoganalytics/ai/openai/openai.py
posthoganalytics/ai/openai/openai_async.py
posthoganalytics/ai/openai/openai_converter.py
posthoganalytics/ai/openai/openai_providers.py
posthoganalytics/ai/openai_agents/__init__.py
posthoganalytics/ai/openai_agents/processor.py
posthoganalytics/integrations/__init__.py
posthoganalytics/integrations/django.py
posthoganalytics/test/__init__.py
posthoganalytics/test/test_before_send.py
posthoganalytics/test/test_client.py
posthoganalytics/test/test_consumer.py
posthoganalytics/test/test_contexts.py
posthoganalytics/test/test_exception_capture.py
posthoganalytics/test/test_feature_flag.py
posthoganalytics/test/test_feature_flag_result.py
posthoganalytics/test/test_feature_flags.py
posthoganalytics/test/test_flag_definition_cache.py
posthoganalytics/test/test_module.py
posthoganalytics/test/test_request.py
posthoganalytics-7.8.0.dist-info/licenses/LICENSE
posthoganalytics-7.8.0.dist-info/METADATA
posthoganalytics-7.8.0.dist-info/WHEEL
posthoganalytics-7.8.0.dist-info/top_level.txt
posthoganalytics-7.8.0.dist-info/RECORD
